blacksmith/__init__.py
blacksmith/cli.py
blacksmith/config/__init__.py
blacksmith/config/loader.py
blacksmith/config/parser.py
blacksmith/config/preferences.py
blacksmith/config/validator.py
blacksmith/export/__init__.py
blacksmith/export/apt.py
blacksmith/export/base.py
blacksmith/export/chocolatey.py
blacksmith/export/pacman.py
blacksmith/export/scoop.py
blacksmith/export/winget.py
blacksmith/package_managers/__init__.py
blacksmith/package_managers/apt.py
blacksmith/package_managers/base.py
blacksmith/package_managers/chocolatey.py
blacksmith/package_managers/detector.py
blacksmith/package_managers/flatpak.py
blacksmith/package_managers/pacman.py
blacksmith/package_managers/scoop.py
blacksmith/package_managers/snap.py
blacksmith/package_managers/winget.py
blacksmith/package_managers/yum.py
blacksmith/sets/__init__.py
blacksmith/sets/cybersecurity.yaml
blacksmith/sets/development.yaml
blacksmith/sets/minimal.yaml
blacksmith/utils/__init__.py
blacksmith/utils/logger.py
blacksmith/utils/os_detector.py
blacksmith/utils/ui.py
jdi_blacksmith-0.2.3.dist-info/licenses/LICENSE
jdi_blacksmith-0.2.3.dist-info/METADATA
jdi_blacksmith-0.2.3.dist-info/WHEEL
jdi_blacksmith-0.2.3.dist-info/entry_points.txt
jdi_blacksmith-0.2.3.dist-info/top_level.txt
jdi_blacksmith-0.2.3.dist-info/RECORD
