Metadata-Version: 2.4
Name: jdi-blacksmith
Version: 0.2.3
Summary: A cross-platform CLI tool for installing development and cybersecurity tools
Author-email: jimididit <jimi.did.it@protonmail.com>
License-Expression: Apache-2.0
Keywords: cli,package-manager,development-tools,cybersecurity
Classifier: Development Status :: 3 - Alpha
Classifier: Intended Audience :: Developers
Classifier: Programming Language :: Python :: 3
Classifier: Programming Language :: Python :: 3.8
Classifier: Programming Language :: Python :: 3.9
Classifier: Programming Language :: Python :: 3.10
Classifier: Programming Language :: Python :: 3.11
Classifier: Programming Language :: Python :: 3.12
Requires-Python: >=3.8
License-File: LICENSE
Requires-Dist: click>=8.1.0
Requires-Dist: rich>=13.0.0
Requires-Dist: questionary>=2.0.0
Requires-Dist: pyyaml>=6.0
Dynamic: license-file
